angre/__init__.py
angre/courses.py
angre/utils.py
angre-0.1.0.dist-info/METADATA
angre-0.1.0.dist-info/WHEEL
angre-0.1.0.dist-info/top_level.txt
angre-0.1.0.dist-info/RECORD
