Metadata-Version: 2.4
Name: angre
Version: 0.1.0
Summary: Consultar cursos de H4U
Home-page: https://hack4u.io
Author: Angre
Dynamic: author
Dynamic: description-content-type
Dynamic: home-page
Dynamic: summary
